.gitignore
LICENSE.txt
README.rst
README.txt
setup.py
motmot/__init__.py
motmot.wxvideo.egg-info/PKG-INFO
motmot.wxvideo.egg-info/SOURCES.txt
motmot.wxvideo.egg-info/dependency_links.txt
motmot.wxvideo.egg-info/namespace_packages.txt
motmot.wxvideo.egg-info/stdeb.cfg
motmot.wxvideo.egg-info/top_level.txt
motmot/wxvideo/__init__.py
motmot/wxvideo/wxvideo.py