Metadata-Version: 1.0
Name: motmot.wxvideo
Version: 0.5.6
Summary: wx viewer of image sequences
Home-page: http://code.astraw.com/projects/motmot
Author: Andrew Straw
Author-email: strawman@astraw.com
License: BSD
Platform: UNKNOWN
